unipolator/__init__.py
unipolator/autobinning.py
unipolator/blas_functions.cp39-win_amd64.pyd
unipolator/blas_functions.pxd
unipolator/blas_functions.pyx
unipolator/blas_functions_vectors.cp39-win_amd64.pyd
unipolator/blas_functions_vectors.pxd
unipolator/blas_functions_vectors.pyx
unipolator/caching.cp39-win_amd64.pyd
unipolator/caching.pxd
unipolator/caching.pyx
unipolator/exp_and_log.cp39-win_amd64.pyd
unipolator/exp_and_log.pxd
unipolator/exp_and_log.pyx
unipolator/hamiltonian_system.cp39-win_amd64.pyd
unipolator/hamiltonian_system.pyx
unipolator/hamiltonian_system_vector.cp39-win_amd64.pyd
unipolator/hamiltonian_system_vector.pyx
unipolator/indexing.cp39-win_amd64.pyd
unipolator/indexing.pxd
unipolator/indexing.pyx
unipolator/sym_trotter_system.cp39-win_amd64.pyd
unipolator/sym_trotter_system.pyx
unipolator/sym_trotter_system_vector.cp39-win_amd64.pyd
unipolator/sym_trotter_system_vector.pyx
unipolator/symmetric_unitary_interpolation.cp39-win_amd64.pyd
unipolator/symmetric_unitary_interpolation.pyx
unipolator/symmetric_unitary_interpolation_vector.cp39-win_amd64.pyd
unipolator/symmetric_unitary_interpolation_vector.pyx
unipolator/trotter_system.cp39-win_amd64.pyd
unipolator/trotter_system.pyx
unipolator/trotter_system_vector.cp39-win_amd64.pyd
unipolator/trotter_system_vector.pyx
unipolator/unitary_interpolation.cp39-win_amd64.pyd
unipolator/unitary_interpolation.pyx
unipolator/unitary_interpolation_vector.cp39-win_amd64.pyd
unipolator/unitary_interpolation_vector.pyx
unipolator-0.3.7.dist-info/LICENSE
unipolator-0.3.7.dist-info/METADATA
unipolator-0.3.7.dist-info/WHEEL
unipolator-0.3.7.dist-info/top_level.txt
unipolator-0.3.7.dist-info/RECORD
