Metadata-Version: 2.1
Name: unipolator
Version: 0.3.7
Summary: Unipolator allows for n dimensional unitary interpolation, and the calculation of propagators using unitary interpolation. Speeds up your propagators for linear quantum systems.
Home-page: https://github.com/Ntropic/unipolator
Download-URL: https://github.com/Ntropic/unipolator/archive/refs/tags/v0.3.7.tar.gz
Author: Michael Schilling
Author-email: michael@ntropic.de
Classifier: Programming Language :: Python :: 3
Classifier: License :: OSI Approved :: MIT License
Classifier: Operating System :: OS Independent
Requires-Python: >=3.4
License-File: LICENSE
Requires-Dist: numpy (>=1.7)
Requires-Dist: scipy (>=1.0)
Requires-Dist: Cython (>=0.29)
Requires-Dist: setuptools (>=65)
Requires-Dist: wheel
Provides-Extra: dev
Requires-Dist: pytest (>=5.1) ; extra == 'dev'
Requires-Dist: flake8 (>=3.7) ; extra == 'dev'
Provides-Extra: docs
Requires-Dist: sphinx ; extra == 'docs'
Requires-Dist: sphinx-rtd-theme ; extra == 'docs'
